{"domain": "stocksafari.com", "description": "Easily, Effortlessly Make 3% To 9% Or Higher ROI (Cash Basis) Every Few Days, Utilizing StockSafari's Price Forecasts (and before using any options, futures).", "parent": {"domain": null}, "tags": ["Renewables & Environment", "B2C"], "indexedAt": "2018-12-27T20:13:10.677Z", "twitter": {"bio": "Easily, Effortlessly Make 3% To 9% Or Higher ROI (Cash Basis) Every Few Days, Utilizing StockSafari's Price Forecasts (and before using any options, futures).", "handle": "forecastall", "site": "http://t.co/YThZcQ8MKx", "followers": 89747, "location": "Internet Space", "following": 42357, "id": "41339860", "avatar": "https://pbs.twimg.com/profile_images/237677111/logo_normal.png"}, "site": {"phoneNumbers": [], "emailAddresses": []}, "linkedin": {"handle": null}, "metrics": {"raised": null, "fiscalYearEnd": null, "employees": null, "annualRevenue": null, "alexaUsRank": null, "marketCap": null, "employeesRange": null, "alexaGlobalRank": 3114350, "estimatedAnnualRevenue": null}, "phone": null, "crunchbase": {"handle": null}, "facebook": {"handle": null, "likes": null}, "timeZone": null, "logo": "https://logo.clearbit.com/stocksafari.com", "geo": {"city": null, "countryCode": null, "subPremise": null, "lat": null, "state": null, "stateCode": null, "streetNumber": null, "country": null, "postalCode": null, "lng": null, "streetName": null}, "id": "0ab9658b-4559-423c-8327-a2e64fe72a02", "category": {"sector": "Utilities", "naicsCode": "33", "industry": "Renewable Electricity", "subIndustry": "Renewable Energy", "sicCode": "35", "industryGroup": "Independent Power and Renewable Electricity Producers"}, "name": "StockSafari Freeware", "ticker": null, "identifiers": {"usEIN": null}, "foundedYear": null, "utcOffset": null, "tech": ["centos", "apache"], "location": null, "legalName": null, "domainAliases": [], "emailProvider": false, "type": "personal"}